Api_Save/ApiTest.py
Api_Save/__init__.py
pyrdt/__init__.py
pyrdt/atom.py
pyrdt/combo.py
pyrdt/math.py
pyrdt/stat.py
pywfz/__init__.py
pywfz/myMath.py
pywfz/sql.py
pywfz/util.py
Api_Save-1.0.1.dist-info/LICENSE
Api_Save-1.0.1.dist-info/METADATA
Api_Save-1.0.1.dist-info/WHEEL
Api_Save-1.0.1.dist-info/top_level.txt
Api_Save-1.0.1.dist-info/RECORD
